{"Response": "Success", "Message": "Total available exchanges - 108", "Data": {"CoinInfo": {"Id": "1182", "Name": "BTC", "FullName": "Bitcoin", "Internal": "BTC", "ImageUrl": "/media/37746251/btc.png", "Url": "/coins/btc/overview", "Algorithm": "SHA-256", "ProofType": "PoW", "TotalCoinsMined": 19035768, "BlockNumber": 735722, "NetHashesPerSecond": 226890081914519900000, "BlockReward": 6.25, "BlockTime": 562, "AssetLaunchDate": "2009-01-03", "MaxSupply": 20999999.9769, "MktCapPenalty": 0, "TotalVolume24H": 747814.9780046829, "TotalTopTierVolume24H": 737520.3462000581}, "AggregatedData": {"TYPE": "5", "MARKET": "CCCAGG", "FROMSYMBOL": "BTC", "TOSYMBOL": "USD", "FLAGS": "2052", "PRICE": 31090.4, "LASTUPDATE": 1652158163, "MEDIAN": 31077.9, "LASTVOLUME": 0.30923591, "LASTVOLUMETO": 9620.9940173065, "LASTTRADEID": "281487868741930", "VOLUMEDAY": 28932.07899346481, "VOLUMEDAYTO": 886576475.2813793, "VOLUME24HOUR": 127908.47943222, "VOLUME24HOURTO": 4034817382.404587, "OPENDAY": 30077.02, "HIGHDAY": 31391.14, "LOWDAY": 29836.19, "OPEN24HOUR": 33647.25, "HIGH24HOUR": 33771.8, "LOW24HOUR": 29754.68, "LASTMARKET": "blockchaincom", "VOLUMEHOUR": 2780.5662787601714, "VOLUMEHOURTO": 85963588.70486735, "OPENHOUR": 30648.56, "HIGHHOUR": 31178.69, "LOWHOUR": 30615.49, "TOPTIERVOLUME24HOUR": 127908.47943222, "TOPTIERVOLUME24HOURTO": 4034817382.404587, "CHANGE24HOUR": -2556.8499999999985, "CHANGEPCT24HOUR": -7.598986544219806, "CHANGEDAY": 1013.380000000001, "CHANGEPCTDAY": 3.369283260110214, "CHANGEHOUR": 441.84000000000015, "CHANGEPCTHOUR": 1.441633799434623, "CONVERSIONTYPE": "direct", "CONVERSIONSYMBOL": "", "SUPPLY": 19035768, "MKTCAP": 591829641427.2001, "MKTCAPPENALTY": 0, "CIRCULATINGSUPPLY": 19035768, "CIRCULATINGSUPPLYMKTCAP": 591829641427.2001, "TOTALVOLUME24H": 747814.9780046829, "TOTALVOLUME24HTO": 23307958385.62189, "TOTALTOPTIERVOLUME24H": 737520.3462000581, "TOTALTOPTIERVOLUME24HTO": 22987894164.963383, "IMAGEURL": "/media/37746251/btc.png"}, "Exchanges": [{"TYPE": "2", "MARKET": "betconix", "FROMSYMBOL": "BTC", "TOSYMBOL": "USD", "FLAGS": "4", "PRICE": 31162.35339, "LASTUPDATE": 1652157902, "LASTVOLUME": 0.001, "LASTVOLUMETO": 31.16235339, "LASTTRADEID": "260778393", "VOLUMEDAY": 84426.60642081, "VOLUMEDAYTO": 2594188852.40154, "VOLUME24HOUR": 631661.09598638, "VOLUME24HOURTO": 20343148329.5419, "OPENDAY": 30261.10188, "HIGHDAY": 31349.717025, "LOWDAY": 29873.07599, "OPEN24HOUR": 33662.94306, "HIGH24HOUR": 33777.130125, "LOW24HOUR": 29873.07599, "VOLUMEHOUR": 4229.83538789, "VOLUMEHOURTO": 130332135.786363, "OPENHOUR": 30663.570545, "HIGHHOUR": 31162.35339, "LOWHOUR": 30663.570545, "CHANGE24HOUR": -2500.5896699999976, "CHANGEPCT24HOUR": -7.4283156571991, "CHANGEDAY": 901.2515100000019, "CHANGEPCTDAY": 2.978250803866637, "CHANGEHOUR": 498.78284500000154, "CHANGEPCTHOUR": 1.6266300242759337}, {"TYPE": "2", "MARKET": "Coinbase", "FROMSYMBOL": "BTC", "TOSYMBOL": "USD", "FLAGS": "1", "PRICE": 31153.96, "LASTUPDATE": 1652158167, "LASTVOLUME": 0.00407029, "LASTVOLUMETO": 126.8056518484, "LASTTRADEID": "330211533", "VOLUMEDAY": 15187.09350947, "VOLUMEDAYTO": 465517862.191965, "VOLUME24HOUR": 64380.72220485, "VOLUME24HOURTO": 2029647580.49716, "OPENDAY": 30078.27, "HIGHDAY": 31450.11, "LOWDAY": 29735.05, "OPEN24HOUR": 33641.94, "HIGH24HOUR": 33761.82, "LOW24HOUR": 29735.05, "VOLUMEHOUR": 1485.71832346, "VOLUMEHOURTO": 45938794.2424487, "OPENHOUR": 30638.85, "HIGHHOUR": 31178.16, "LOWHOUR": 30594.49, "CHANGE24HOUR": -2487.980000000003, "CHANGEPCT24HOUR": -7.395471248090933, "CHANGEDAY": 1075.6899999999987, "CHANGEPCTDAY": 3.5763027594339656, "CHANGEHOUR": 515.1100000000006, "CHANGEPCTHOUR": 1.6812315083627505, "CONVERSIONTYPE": "force_direct", "CONVERSIONSYMBOL": "", "SUPPLY": 19035768, "MKTCAP": 593039554841.28, "MKTCAPPENALTY": 0, "CIRCULATINGSUPPLY": 19035768, "CIRCULATINGSUPPLYMKTCAP": 593039554841.28, "TOTALVOLUME24HTO": 0, "TOTALVOLUME24H": 0, "TOTALTOPTIERVOLUME24HTO": 0, "TOTALTOPTIERVOLUME24H": 0, "IMAGEURL": "/media/37746251/btc.png"}, {"TYPE": "2", "MARKET": "ftx", "FROMSYMBOL": "BTC", "TOSYMBOL": "USD", "FLAGS": "4", "PRICE": 31134, "LASTUPDATE": 1652158168, "LASTVOLUME": 0.4192, "LASTVOLUMETO": 13051.3728, "LASTTRADEID": "3943749980", "VOLUMEDAY": 10707.4392, "VOLUMEDAYTO": 328211320.7847, "VOLUME24HOUR": 60198.6741, "VOLUME24HOURTO": 1908983082.7272, "OPENDAY": 30096, "HIGHDAY": 31428, "LOWDAY": 29721, "OPEN24HOUR": 33629, "HIGH24HOUR": 33766, "LOW24HOUR": 29721, "VOLUMEHOUR": 1248.7776, "VOLUMEHOURTO": 38648203.9776, "OPENHOUR": 30643, "HIGHHOUR": 31179, "LOWHOUR": 30600, "CHANGE24HOUR": -2495, "CHANGEPCT24HOUR": -7.419191769008891, "CHANGEDAY": 1038, "CHANGEPCTDAY": 3.4489633173843703, "CHANGEHOUR": 491, "CHANGEPCTHOUR": 1.6023235322912246}, {"TYPE": "2", "MARKET": "bullish", "FROMSYMBOL": "BTC", "TOSYMBOL": "USD", "FLAGS": "1", "PRICE": 31091.0004, "LASTUPDATE": 1652158162, "LASTVOLUME": 0.3073, "LASTVOLUMETO": 9554.26442292, "LASTTRADEID": "29043", "VOLUMEDAY": 6986.48065998, "VOLUMEDAYTO": 216649040.848151, "VOLUME24HOUR": 26991.7588972, "VOLUME24HOURTO": 858011689.336741, "OPENDAY": 31362.225, "HIGHDAY": 31362.225, "LOWDAY": 30698.5883, "OPEN24HOUR": 33699.0672, "HIGH24HOUR": 33755.6955, "LOW24HOUR": 30698.5883, "VOLUMEHOUR": 932.28866482, "VOLUMEHOURTO": 28864221.6381037, "OPENHOUR": 30727.262, "HIGHHOUR": 31157.805, "LOWHOUR": 30698.5883, "CHANGE24HOUR": -2608.066799999997, "CHANGEPCT24HOUR": -7.739284842875405, "CHANGEDAY": -271.22459999999774, "CHANGEPCTDAY": -0.8648130035416739, "CHANGEHOUR": 363.738400000002, "CHANGEPCTHOUR": 1.18376443693552}, {"TYPE": "2", "MARKET": "Bitfinex", "FROMSYMBOL": "BTC", "TOSYMBOL": "USD", "FLAGS": "4", "PRICE": 31160, "LASTUPDATE": 1652158169, "LASTVOLUME": 0.0064, "LASTVOLUMETO": 199.424, "LASTTRADEID": "1090312061", "VOLUMEDAY": 3777.86039338, "VOLUMEDAYTO": 115484071.348977, "VOLUME24HOUR": 23191.65988892, "VOLUME24HOURTO": 736007604.441091, "OPENDAY": 30140, "HIGHDAY": 31485, "LOWDAY": 29833, "OPEN24HOUR": 33680, "HIGH24HOUR": 33815, "LOW24HOUR": 29833, "VOLUMEHOUR": 249.76777836, "VOLUMEHOURTO": 7733954.37367912, "OPENHOUR": 30692, "HIGHHOUR": 31220, "LOWHOUR": 30650, "CHANGE24HOUR": -2520, "CHANGEPCT24HOUR": -7.4821852731591445, "CHANGEDAY": 1020, "CHANGEPCTDAY": 3.3842070338420704, "CHANGEHOUR": 468, "CHANGEPCTHOUR": 1.5248273165645772}]}, "RateLimit": {}, "HasWarning": false, "Type": 100}